README.rst
setup.py
aiowrap/__init__.py
aiowrap/wrap.py
aiowrap.egg-info/PKG-INFO
aiowrap.egg-info/SOURCES.txt
aiowrap.egg-info/dependency_links.txt
aiowrap.egg-info/requires.txt
aiowrap.egg-info/top_level.txt