Metadata-Version: 1.0
Name: aiowrap
Version: 0.1.1
Summary: Tools for wrapping existing synchronous libraries into Python3's asyncio framework.
Home-page: UNKNOWN
Author: iceboy
Author-email: me@iceboy.org
License: http://www.apache.org/licenses/LICENSE-2.0
Keywords: asyncio greenlet wrap
Platform: UNKNOWN
